thermohw/__init__.py
thermohw/_version.py
thermohw/convert_thermo_hw.py
thermohw/extract_attachments.py
thermohw/filters.py
thermohw/homework.tpl
thermohw/preprocessors.py
thermohw/pymarkdown.py
thermohw/utils.py
thermohw-0.7.1.dist-info/LICENSE
thermohw-0.7.1.dist-info/METADATA
thermohw-0.7.1.dist-info/WHEEL
thermohw-0.7.1.dist-info/entry_points.txt
thermohw-0.7.1.dist-info/top_level.txt
thermohw-0.7.1.dist-info/RECORD
