Metadata-Version: 2.1
Name: thermohw
Version: 0.7.1
Summary: Package for converting thermo homework assignments
Home-page: https://github.com/bryanwweber/thermohw
Author: Bryan W. Weber
Maintainer: Bryan W. Weber
Maintainer-email: bryan.w.weber@gmail.com
License: BSD-3-clause
Project-URL: Source, https://github.com/bryanwweber/thermohw
Project-URL: Tracker, https://github.com/bryanwweber/thermohw/issues
Keywords: thermodynamics homework pdf jupyter notebook
Platform: any
Classifier: Development Status :: 3 - Alpha
Classifier: Intended Audience :: Developers
Classifier: Intended Audience :: Science/Research
Classifier: Intended Audience :: Education
Classifier: License :: OSI Approved :: BSD License
Classifier: Natural Language :: English
Classifier: Programming Language :: Python :: 3
Classifier: Programming Language :: Python :: 3.7
Classifier: Programming Language :: Python :: 3.8
Classifier: Programming Language :: Python :: 3.9
Classifier: Topic :: Scientific/Engineering :: Chemistry
Requires-Python: ~=3.7
Requires-Dist: nbconvert (<6.0,>=5.5)
Requires-Dist: traitlets (<5.0,>=4.3)
Requires-Dist: pdfrw (<0.5,>=0.4)
Requires-Dist: pandocfilters (<2.0,>=1.4)
Requires-Dist: ipython (<8.0,>=7.0)
Provides-Extra: testing
Requires-Dist: pytest (>=3.2.0) ; extra == 'testing'
